winding/__init__.py
winding/ast.py
winding/grammar.py
winding/parser.py
winding/transformer.py
winding-0.4.1.dist-info/METADATA
winding-0.4.1.dist-info/WHEEL
winding-0.4.1.dist-info/entry_points.txt
winding-0.4.1.dist-info/top_level.txt
winding-0.4.1.dist-info/RECORD
