Metadata-Version: 2.1
Name: winding
Version: 0.4.1
Summary: A Python implementation of Winding Markdown, illuminate tooling, parser and EBNF.
Home-page: https://winding.md
Author: Wind
Author-email: wind@wind.kids
License: MIT
Project-URL: Source, https://github.com/Wind-WindKids/winding
Keywords: winding.md,winding,Winding,markdown,parser,illuminate,typesetting,Smalltalk
Classifier: Programming Language :: Python :: 3
Classifier: License :: OSI Approved :: MIT License
Classifier: Operating System :: OS Independent
Requires-Python: >=3.10
Provides-Extra: illuminate
Requires-Dist: openai; extra == "illuminate"
Requires-Dist: Pillow; extra == "illuminate"
Requires-Dist: opencv-python; extra == "illuminate"
